setup.py
inowfaasutils/__init__.py
inowfaasutils.egg-info/PKG-INFO
inowfaasutils.egg-info/SOURCES.txt
inowfaasutils.egg-info/dependency_links.txt
inowfaasutils.egg-info/not-zip-safe
inowfaasutils.egg-info/requires.txt
inowfaasutils.egg-info/top_level.txt
inowfaasutils/callback/__init__.py
inowfaasutils/callback/base.py
inowfaasutils/callback/pubsub.py
inowfaasutils/callback/webhook.py
inowfaasutils/comm/__init__.py
inowfaasutils/comm/http.py
inowfaasutils/comm/pubsub.py
inowfaasutils/decorators/__init__.py
inowfaasutils/decorators/http.py
inowfaasutils/decorators/pubsub.py
inowfaasutils/faasjob/__init__.py
inowfaasutils/faasjob/model.py
inowfaasutils/logger/__init__.py
inowfaasutils/misc/__init__.py
inowfaasutils/misc/dataclass_helper.py
inowfaasutils/misc/enum.py
inowfaasutils/misc/exception.py
inowfaasutils/misc/model.py
inowfaasutils/misc/singleton.py
inowfaasutils/storage/__init__.py
inowfaasutils/storage/firestore.py