Metadata-Version: 2.1
Name: inowfaasutils
Version: 0.0.71
Summary: Influencer Now Google Cloud FaaS Utilities
Home-page: UNKNOWN
Author: Iván Huerta
Author-email: contacto@influencernow.cl
License: unlicense
Platform: UNKNOWN
Requires-Python: >=3.8
Provides-Extra: all
Provides-Extra: faasjob
Provides-Extra: comm
Provides-Extra: datastore
